ezstat.py
ezstat-2.4.dist-info/WHEEL
ezstat-2.4.dist-info/METADATA
ezstat-2.4.dist-info/RECORD
