Metadata-Version: 2.1
Name: ezstat
Version: 2.4
Summary: OOP For eazy statistics, inspired by `Statistics` class of the lib `deap` but more user-friendly
Home-page: https://github.com/Freakwill/ezstat
License: MIT
Keywords: Statistics,Genetic Algorithm
Author: William Song
Author-email: 30965609+Freakwill@users.noreply.github.com
Requires-Python: >=3.9,<4.0
Classifier: Environment :: MacOS X
Classifier: Intended Audience :: Science/Research
Classifier: License :: OSI Approved :: MIT License
Classifier: Operating System :: OS Independent
Classifier: Programming Language :: Python :: 3
Classifier: Programming Language :: Python :: 3.10
Classifier: Programming Language :: Python :: 3.9
Classifier: Topic :: Scientific/Engineering :: Mathematics
Classifier: Topic :: Software Development :: Libraries :: Python Modules
Project-URL: Repository, https://github.com/Freakwill/ezstat
